HousePricePrediction/__init__.py
HousePricePrediction/ingest_data.py
HousePricePrediction/score.py
HousePricePrediction/train.py
HousePricePrediction_6123-0.2.dist-info/METADATA
HousePricePrediction_6123-0.2.dist-info/WHEEL
HousePricePrediction_6123-0.2.dist-info/top_level.txt
HousePricePrediction_6123-0.2.dist-info/RECORD
