Metadata-Version: 2.1
Name: HousePricePrediction_6123
Version: 0.2
Requires-Dist: numpy
Requires-Dist: pandas
Requires-Dist: scikit-learn
Requires-Dist: scipy
